ai_exporter/__init__.py
ai_exporter/core.py
ai_exporter/parsers/__init__.py
ai_exporter/parsers/base.py
ai_exporter/parsers/chatgpt.py
ai_exporter/parsers/claude.py
ai_exporter/parsers/deepseek.py
ai_exporter/parsers/qwen.py
ai_exporter/parsers/universal.py
ai_conversation_exporter-0.1.0.dist-info/METADATA
ai_conversation_exporter-0.1.0.dist-info/WHEEL
ai_conversation_exporter-0.1.0.dist-info/entry_points.txt
ai_conversation_exporter-0.1.0.dist-info/top_level.txt
ai_conversation_exporter-0.1.0.dist-info/RECORD
