Metadata-Version: 2.4
Name: ai-conversation-exporter
Version: 0.1.0
Summary: Export conversations from multiple AI platforms (ChatGPT, DeepSeek, Claude) to Markdown
Author-email: toke648 <tim16673802@gmail.com>
License: MIT
Project-URL: Homepage, https://github.com/yourusername/ai-exporter
Keywords: chatgpt,deepseek,claude,export,markdown,ai
Classifier: Development Status :: 4 - Beta
Classifier: Intended Audience :: End Users/Desktop
Classifier: License :: OSI Approved :: MIT License
Classifier: Programming Language :: Python :: 3
Classifier: Programming Language :: Python :: 3.7
Classifier: Programming Language :: Python :: 3.8
Classifier: Programming Language :: Python :: 3.9
Classifier: Programming Language :: Python :: 3.10
Classifier: Programming Language :: Python :: 3.11
Requires-Python: >=3.7
